setup.py
ThreadDownloader8527.egg-info/PKG-INFO
ThreadDownloader8527.egg-info/SOURCES.txt
ThreadDownloader8527.egg-info/dependency_links.txt
ThreadDownloader8527.egg-info/top_level.txt
simplethreading/__init__.py
simplethreading/threadPool.py
simplethreading/threadingbyfunction.py