Metadata-Version: 1.0
Name: ThreadDownloader8527
Version: 1.0.2
Summary: my first python distribution
Home-page: UNKNOWN
Author: UNKNOWN
Author-email: UNKNOWN
License: UNKNOWN
Platform: UNKNOWN
